tcg_research_desk/__init__.py
tcg_research_desk/archetypes.py
tcg_research_desk/html_vis.py
tcg_research_desk/process_data.py
tcg_research_desk/resources/MTG_Bazaar_LOGO_PNG-02.png
tcg_research_desk/resources/team_bus_stop_full_colour.png
tcg_research_desk/ui.py
tcg_research_desk/ui_helpers.py
tcg_research_desk/utils.py
tcg_research_desk-1.0.2.dist-info/LICENSE
tcg_research_desk-1.0.2.dist-info/METADATA
tcg_research_desk-1.0.2.dist-info/WHEEL
tcg_research_desk-1.0.2.dist-info/RECORD
