Metadata-Version: 2.3
Name: tcg-research-desk
Version: 1.0.2
Summary: Tools to analyze and build dashboards for trading card game tournaments
Author: ArcKayNine
Requires-Python: >=3.9
Classifier: Programming Language :: Python :: 3
Classifier: Programming Language :: Python :: 3.9
Classifier: Programming Language :: Python :: 3.10
Classifier: Programming Language :: Python :: 3.11
Classifier: Programming Language :: Python :: 3.12
Classifier: Programming Language :: Python :: 3.13
Requires-Dist: bokeh (>=3.7.3)
Requires-Dist: holoviews (>=1.21.0)
Requires-Dist: numpy (>=2.2.5)
Requires-Dist: pandas (>=2.3.1)
Requires-Dist: panel (>=1.8.0)
Requires-Dist: param (>=2.2.1)
Requires-Dist: scikit-learn (>=1.7.0)
Requires-Dist: scipy (>=1.14.1)
